README.txt
setup.py
docs/HISTORY.txt
valentine/__init__.py
valentine.multiparagraphfield.egg-info/PKG-INFO
valentine.multiparagraphfield.egg-info/SOURCES.txt
valentine.multiparagraphfield.egg-info/dependency_links.txt
valentine.multiparagraphfield.egg-info/entry_points.txt
valentine.multiparagraphfield.egg-info/namespace_packages.txt
valentine.multiparagraphfield.egg-info/not-zip-safe
valentine.multiparagraphfield.egg-info/requires.txt
valentine.multiparagraphfield.egg-info/top_level.txt
valentine/multiparagraphfield/TODO
valentine/multiparagraphfield/__init__.py
valentine/multiparagraphfield/configure.zcml
valentine/multiparagraphfield/utils.py
valentine/multiparagraphfield/field/__init__.py
valentine/multiparagraphfield/field/multiparagraphfield.py
valentine/multiparagraphfield/widget/__init__.py
valentine/multiparagraphfield/widget/configure.zcml
valentine/multiparagraphfield/widget/multiparagraphwidget.pt
valentine/multiparagraphfield/widget/multiparagraphwidget.py
valentine/multiparagraphfield/widget/multiparagraphwidgetmacros.py
valentine/multiparagraphfield/widget/newparagraph.pt