Metadata-Version: 1.0
Name: valentine.multiparagraphfield
Version: 0.4
Summary: Field that handles multiple TextFields+RichWidgets as one field.
Home-page: http://svn.plone.org/svn/collective/valentine.multiparagraphfield/trunk/
Author: Sasha Vincic
Author-email: sasha dot vincic at valentinwebsystems dot com
License: GPL
Keywords: archetypes,plone,atfield,kupu,richtext,richwidget,tinymce
Platform: UNKNOWN
Classifier: Programming Language :: Python
